grapheneapi/__init__.py
grapheneapi/api.py
grapheneapi/exceptions.py
grapheneapi/grapheneapi.py
grapheneapi/http.py
grapheneapi/rpc.py
grapheneapi/websocket.py
grapheneapi/aio/__init__.py
grapheneapi/aio/api.py
grapheneapi/aio/http.py
grapheneapi/aio/rpc.py
grapheneapi/aio/websocket.py
graphenebase/__init__.py
graphenebase/account.py
graphenebase/aes.py
graphenebase/base58.py
graphenebase/bip38.py
graphenebase/chains.py
graphenebase/dictionary.py
graphenebase/ecdsa.py
graphenebase/memo.py
graphenebase/objects.py
graphenebase/objecttypes.py
graphenebase/operationids.py
graphenebase/operations.py
graphenebase/prefix.py
graphenebase/ripemd160.py
graphenebase/signedtransactions.py
graphenebase/transactions.py
graphenebase/types.py
graphenebase/utils.py
graphenecommon/__init__.py
graphenecommon/account.py
graphenecommon/amount.py
graphenecommon/asset.py
graphenecommon/block.py
graphenecommon/blockchain.py
graphenecommon/blockchainobject.py
graphenecommon/chain.py
graphenecommon/committee.py
graphenecommon/exceptions.py
graphenecommon/genesisbalance.py
graphenecommon/instance.py
graphenecommon/memo.py
graphenecommon/message.py
graphenecommon/objectcache.py
graphenecommon/price.py
graphenecommon/proposal.py
graphenecommon/transactionbuilder.py
graphenecommon/utils.py
graphenecommon/vesting.py
graphenecommon/wallet.py
graphenecommon/witness.py
graphenecommon/worker.py
graphenecommon/aio/__init__.py
graphenecommon/aio/account.py
graphenecommon/aio/amount.py
graphenecommon/aio/asset.py
graphenecommon/aio/block.py
graphenecommon/aio/blockchain.py
graphenecommon/aio/blockchainobject.py
graphenecommon/aio/chain.py
graphenecommon/aio/committee.py
graphenecommon/aio/genesisbalance.py
graphenecommon/aio/instance.py
graphenecommon/aio/memo.py
graphenecommon/aio/message.py
graphenecommon/aio/price.py
graphenecommon/aio/proposal.py
graphenecommon/aio/transactionbuilder.py
graphenecommon/aio/vesting.py
graphenecommon/aio/wallet.py
graphenecommon/aio/witness.py
graphenelib-1.6.0.dist-info/LICENSE.txt
graphenelib-1.6.0.dist-info/METADATA
graphenelib-1.6.0.dist-info/WHEEL
graphenelib-1.6.0.dist-info/top_level.txt
graphenelib-1.6.0.dist-info/RECORD
